LICENSE
MANIFEST.in
README.rst
setup.py
beets_bandcamp.egg-info/PKG-INFO
beets_bandcamp.egg-info/SOURCES.txt
beets_bandcamp.egg-info/dependency_links.txt
beets_bandcamp.egg-info/requires.txt
beets_bandcamp.egg-info/top_level.txt
beetsplug/__init__.py
beetsplug/bandcamp.py