Metadata-Version: 1.1
Name: beets-bandcamp
Version: 0.1.2
Summary: Plugin for beets (http://beets.io) to use bandcamp as an autotagger source.
Home-page: https://github.com/unrblt/beets-bandcamp
Author: Ariel George
Author-email: unarbolito@gmail.com
License: GPL-2.0
Download-URL: https://github.com/unrblt/beets-bandcamp/archive/v0.1.2.tar.gz
Platform: ALL
Classifier: Topic :: Multimedia :: Sound/Audio
Classifier: Topic :: Multimedia :: Sound/Audio :: Players :: MP3
Classifier: License :: OSI Approved :: GNU General Public License (GPL)
Classifier: Environment :: Console
Classifier: Environment :: Web Environment
Classifier: Programming Language :: Python :: 2
Classifier: Programming Language :: Python :: 2.6
Classifier: Programming Language :: Python :: 2.7
